liquichain/__init__.py
liquichain/api/__init__.py
liquichain/api/client.py
liquichain/api/error.py
liquichain/api/version.py
liquichain/api/objects/__init__.py
liquichain/api/objects/base.py
liquichain/api/objects/capture.py
liquichain/api/objects/chargeback.py
liquichain/api/objects/customer.py
liquichain/api/objects/invoice.py
liquichain/api/objects/issuer.py
liquichain/api/objects/list.py
liquichain/api/objects/mandate.py
liquichain/api/objects/method.py
liquichain/api/objects/onboarding.py
liquichain/api/objects/order.py
liquichain/api/objects/order_line.py
liquichain/api/objects/organization.py
liquichain/api/objects/payment.py
liquichain/api/objects/payment_link.py
liquichain/api/objects/permission.py
liquichain/api/objects/profile.py
liquichain/api/objects/refund.py
liquichain/api/objects/settlement.py
liquichain/api/objects/shipment.py
liquichain/api/objects/subscription.py
liquichain/api/resources/__init__.py
liquichain/api/resources/base.py
liquichain/api/resources/captures.py
liquichain/api/resources/chargebacks.py
liquichain/api/resources/customer_mandates.py
liquichain/api/resources/customer_payments.py
liquichain/api/resources/customer_subscriptions.py
liquichain/api/resources/customers.py
liquichain/api/resources/invoices.py
liquichain/api/resources/methods.py
liquichain/api/resources/onboarding.py
liquichain/api/resources/order_lines.py
liquichain/api/resources/order_payments.py
liquichain/api/resources/order_refunds.py
liquichain/api/resources/orders.py
liquichain/api/resources/organizations.py
liquichain/api/resources/payment_chargebacks.py
liquichain/api/resources/payment_links.py
liquichain/api/resources/payment_refunds.py
liquichain/api/resources/payments.py
liquichain/api/resources/permissions.py
liquichain/api/resources/profile_chargebacks.py
liquichain/api/resources/profile_methods.py
liquichain/api/resources/profile_payments.py
liquichain/api/resources/profile_refunds.py
liquichain/api/resources/profiles.py
liquichain_api_python-0.1.1.dist-info/LICENSE.txt
liquichain_api_python-0.1.1.dist-info/METADATA
liquichain_api_python-0.1.1.dist-info/WHEEL
liquichain_api_python-0.1.1.dist-info/top_level.txt
liquichain_api_python-0.1.1.dist-info/RECORD
