Metadata-Version: 2.1
Name: liquichain-api-python
Version: 0.1.1
Summary: Liquichain API client for Python
Home-page: https://github.com/liquichain/Liquichain-api-python
Author: Liquichain
Author-email: contact@liquichain.io
Maintainer: Manaty SARL
Maintainer-email: contact@manaty.net
License: BSD
Keywords: liquichain,blockchain,cryptocurrency,payment,service,direct debit,refunds,payments,gateway
Platform: UNKNOWN
Classifier: Programming Language :: Python
Classifier: Programming Language :: Python :: 3
Classifier: Development Status :: 2 - Pre-Alpha
Classifier: Intended Audience :: Developers
Classifier: License :: OSI Approved :: BSD License
Classifier: Topic :: Office/Business :: Financial
License-File: LICENSE.txt
Requires-Dist: requests
Requires-Dist: urllib3
Requires-Dist: requests-oauthlib
